Workbook
Name Category: Setup!$E$3:$E$12
Name Payment: Setup!$A$3:$A$5

Sheet Setup
A1: MONTHLY PLAN | E1: EXPENSE CATEGORIES
A2: Payment Mode | B2: Monthly Balance | C2: Remaining | E2: Category | F2: Spent
A3: Indian Bank | B3: 1000 | C3: =B3-SUMIFS('Daily Tracker'!D:D,'Daily Tracker'!C:C,A3) -> 960 | E3: Room Rent | F3: =SUMIFS('Daily Tracker'!D:D,'Daily Tracker'!B:B,E3) -> 3750
A4: HDFC Bank | B4: 25000 | C4: =B4-SUMIFS('Daily Tracker'!D:D,'Daily Tracker'!C:C,A4) -> 20750 | E4: Parents | F4: =SUMIFS('Daily Tracker'!D:D,'Daily Tracker'!B:B,E4) -> 0
A5: Cash | B5: 10000 | C5: =B5-SUMIFS('Daily Tracker'!D:D,'Daily Tracker'!C:C,A5) -> 9840 | E5: Fuel | F5: =SUMIFS('Daily Tracker'!D:D,'Daily Tracker'!B:B,E5) -> 0
A6: Total | B6: =SUM(B3:B5) -> 36000 | C6: =SUM(C3:C5) -> 31550 | E6: Groceries | F6: =SUMIFS('Daily Tracker'!D:D,'Daily Tracker'!B:B,E6) -> 70
E7: Eating Out | F7: =SUMIFS('Daily Tracker'!D:D,'Daily Tracker'!B:B,E7) -> 90
E8: Transport | F8: =SUMIFS('Daily Tracker'!D:D,'Daily Tracker'!B:B,E8) -> 0
E9: Mobile/Wifi | F9: =SUMIFS('Daily Tracker'!D:D,'Daily Tracker'!B:B,E9) -> 0
E10: Medicine | F10: =SUMIFS('Daily Tracker'!D:D,'Daily Tracker'!B:B,E10) -> 0
E11: Shopping | F11: =SUMIFS('Daily Tracker'!D:D,'Daily Tracker'!B:B,E11) -> 0
E12: Extra | F12: =SUMIFS('Daily Tracker'!D:D,'Daily Tracker'!B:B,E12) -> 500
E13: Total | F13: =SUM(F3:F12) -> 4410

Sheet Daily Tracker
A1: DAILY EXPENSE TRACKER
A2: Date | B2: Description | C2: Payment Mode | D2: Amount | E2: Balance
A3: 46082 | B3: Room Rent | C3: HDFC Bank | D3: 3750 | E3: =IFERROR(VLOOKUP(C3,Setup!$A$3:$B$5,2,FALSE)-SUMIFS(D$3:D3,C$3:C3,C3),"") -> 21250
A4: 46083 | B4: Extra | C4: HDFC Bank | D4: 500 | E4: =IFERROR(VLOOKUP(C4,Setup!$A$3:$B$5,2,FALSE)-SUMIFS(D$3:D4,C$3:C4,C4),"") -> 20750
A5: 46083 | B5: Groceries | C5: Cash | D5: 70 | E5: =IFERROR(VLOOKUP(C5,Setup!$A$3:$B$5,2,FALSE)-SUMIFS(D$3:D5,C$3:C5,C5),"") -> 9930
B6: Eating Out | C6: Cash | D6: 90 | E6: =IFERROR(VLOOKUP(C6,Setup!$A$3:$B$5,2,FALSE)-SUMIFS(D$3:D6,C$3:C6,C6),"") -> 9840
C7: Indian Bank | D7: 40 | E7: =IFERROR(VLOOKUP(C7,Setup!$A$3:$B$5,2,FALSE)-SUMIFS(D$3:D7,C$3:C7,C7),"") -> 960

Sheet Dashboard
A1: 📊 MONTHLY DASHBOARD
A3: Total Budget | B3: =Setup!B6 -> 36000
A4: Total Spent | B4: =Setup!F13 -> 4410
A5: Total Remaining | B5: =B3-B4 -> 31590
A6: Days Left | B6: =EOMONTH(TODAY(),0)-TODAY() -> 28
A7: Daily Average Spend | B7: =IFERROR(B4/DAY(TODAY()),"") -> 1470
A9: PAYMENT MODE | B9: Balance | C9: Remaining
A10: Indian Bank | B10: =Setup!B3 -> 1000 | C10: =Setup!C3 -> 960
A11: HDFC Bank | B11: =Setup!B4 -> 25000 | C11: =Setup!C4 -> 20750
A12: Cash | B12: =Setup!B5 -> 10000 | C12: =Setup!C5 -> 9840
A13: Total | B13: =Setup!B6 -> 36000 | C13: =Setup!C6 -> 31550
A15: CATEGORY | B15: Spent
A16: Room Rent | B16: =Setup!F3 -> 3750
A17: Parents | B17: =Setup!F4 -> 0
A18: Fuel | B18: =Setup!F5 -> 0
A19: Groceries | B19: =Setup!F6 -> 70
A20: Eating Out | B20: =Setup!F7 -> 90
A21: Transport | B21: =Setup!F8 -> 0
A22: Mobile/Wifi | B22: =Setup!F9 -> 0
A23: Medicine | B23: =Setup!F10 -> 0
A24: Shopping | B24: =Setup!F11 -> 0
A25: Extra | B25: =Setup!F12 -> 500
A26: Total | B26: =Setup!F13 -> 4410
